lab4/axis_data_fifo.v
`timescale 1ns / 1ps

module axis_fifo #
(
    parameter ADDR_WIDTH = 12,
    parameter AXIS_DATA_WIDTH = 32
)
(
    /*
     * Ports to pipe in the data to the FIFO
     */
    input  wire                   wr_aclk,
    input  wire                   wr_rstn,
    input  wire [AXIS_DATA_WIDTH-1:0]  wr_axis_data,
    input  wire                   wr_axis_vld,
    output wire                   wr_axis_rdy,

    /*
     * Ports to get the data to the FIFO
     */
    input  wire                   rd_aclk,
    input  wire                   rd_rstn,
    output wire [AXIS_DATA_WIDTH-1:0]  rd_axis_data,
    output wire                   rd_axis_vld,
    input  wire                   rd_axis_rdy
);

reg [ADDR_WIDTH:0] wr_ptr_reg = {ADDR_WIDTH+1{1'b0}}, wr_ptr_next;
reg [ADDR_WIDTH:0] wr_ptr_gray_reg = {ADDR_WIDTH+1{1'b0}}, wr_ptr_gray_next;
reg [ADDR_WIDTH:0] wr_addr_reg = {ADDR_WIDTH+1{1'b0}};
reg [ADDR_WIDTH:0] rd_ptr_reg = {ADDR_WIDTH+1{1'b0}}, rd_ptr_next;
reg [ADDR_WIDTH:0] rd_ptr_gray_reg = {ADDR_WIDTH+1{1'b0}}, rd_ptr_gray_next;
reg [ADDR_WIDTH:0] rd_addr_reg = {ADDR_WIDTH+1{1'b0}};

reg [ADDR_WIDTH:0] wr_ptr_gray_sync1_reg = {ADDR_WIDTH+1{1'b0}};
reg [ADDR_WIDTH:0] wr_ptr_gray_sync2_reg = {ADDR_WIDTH+1{1'b0}};
reg [ADDR_WIDTH:0] rd_ptr_gray_sync1_reg = {ADDR_WIDTH+1{1'b0}};
reg [ADDR_WIDTH:0] rd_ptr_gray_sync2_reg = {ADDR_WIDTH+1{1'b0}};

reg wr_rst_sync1_reg = 1'b1;
reg wr_rst_sync2_reg = 1'b1;
reg wr_rst_sync3_reg = 1'b1;
reg rd_rst_sync1_reg = 1'b1;
reg rd_rst_sync2_reg = 1'b1;
reg rd_rst_sync3_reg = 1'b1;

reg [AXIS_DATA_WIDTH+1-1:0] mem[(2**ADDR_WIDTH)-1:0];
reg [AXIS_DATA_WIDTH+1-1:0] mem_read_data_reg = {AXIS_DATA_WIDTH+1{1'b0}};
reg mem_read_data_valid_reg = 1'b0, mem_read_data_valid_next;
wire [AXIS_DATA_WIDTH+1-1:0] mem_write_data;

reg [AXIS_DATA_WIDTH+1-1:0] rd_data_reg = {AXIS_DATA_WIDTH+1{1'b0}};

reg rd_axis_vld_reg = 1'b0, rd_axis_vld_next;

// TODO: check for full status based on comparison between wr_ptr_gray_reg and rd_ptr_gray_sync2_reg
wire full = (wr_ptr_gray_reg[ADDR_WIDTH]     != rd_ptr_gray_sync2_reg[ADDR_WIDTH])
         && (wr_ptr_gray_reg[ADDR_WIDTH-1]   != rd_ptr_gray_sync2_reg[ADDR_WIDTH-1])
         && (wr_ptr_gray_reg[ADDR_WIDTH-2:0] == rd_ptr_gray_sync2_reg[ADDR_WIDTH-2:0]);

// TODO: check for empty status based on comparison between wr_ptr_gray_reg and rd_ptr_gray_sync2_reg
wire empty = (rd_ptr_gray_reg == wr_ptr_gray_sync2_reg);

// control signals
reg write;
reg read;
reg store_output;

// TODO: complete the logic for wr_axis_rdy
assign wr_axis_rdy = ~full & ~wr_rst_sync3_reg;

assign rd_axis_vld = rd_axis_vld_reg;

assign mem_write_data[AXIS_DATA_WIDTH-1:0] = wr_axis_data;
assign rd_axis_data = rd_data_reg[AXIS_DATA_WIDTH-1:0];

// reset synchronization
always @(posedge wr_aclk) begin
    if (!wr_rstn) begin
        wr_rst_sync1_reg <= 1'b1;
        wr_rst_sync2_reg <= 1'b1;
        wr_rst_sync3_reg <= 1'b1;
    end else begin
        wr_rst_sync1_reg <= 1'b0;
        wr_rst_sync2_reg <= wr_rst_sync1_reg | rd_rst_sync1_reg;
        wr_rst_sync3_reg <= wr_rst_sync2_reg;
    end
end

always @(posedge rd_aclk) begin
    if (!rd_rstn) begin
        rd_rst_sync1_reg <= 1'b1;
        rd_rst_sync2_reg <= 1'b1;
        rd_rst_sync3_reg <= 1'b1;
    end else begin
        rd_rst_sync1_reg <= 1'b0;
        rd_rst_sync2_reg <= wr_rst_sync1_reg | rd_rst_sync1_reg;
        rd_rst_sync3_reg <= rd_rst_sync2_reg;
    end
end

// Write logic
always @* begin
    write = 1'b0;

    wr_ptr_next = wr_ptr_reg;
    wr_ptr_gray_next = wr_ptr_gray_reg;

    //TODO: complete the write logic; hint should we always execute the the following signal assignments? or is there a condition that we should check?
    // ts is doneeeeee

    if (wr_axis_vld && wr_axis_rdy) begin
        write = 1'b1;
        wr_ptr_next = wr_ptr_reg + 1;
        wr_ptr_gray_next = wr_ptr_next ^ (wr_ptr_next >> 1);
    end
end

always @(posedge wr_aclk) begin
    if (wr_rst_sync3_reg) begin
        wr_ptr_reg <= {ADDR_WIDTH+1{1'b0}};
        wr_ptr_gray_reg <= {ADDR_WIDTH+1{1'b0}};
    end else begin
        wr_ptr_reg <= wr_ptr_next;
        wr_ptr_gray_reg <= wr_ptr_gray_next;
    end

    wr_addr_reg <= wr_ptr_next;

    if (write) begin
        mem[wr_addr_reg[ADDR_WIDTH-1:0]] <= mem_write_data;
    end
end

// pointer synchronization
always @(posedge wr_aclk) begin
    if (wr_rst_sync3_reg) begin
        rd_ptr_gray_sync1_reg <= {ADDR_WIDTH+1{1'b0}};
        rd_ptr_gray_sync2_reg <= {ADDR_WIDTH+1{1'b0}};
    end else begin
        rd_ptr_gray_sync1_reg <= rd_ptr_gray_reg;
        rd_ptr_gray_sync2_reg <= rd_ptr_gray_sync1_reg;
    end
end

always @(posedge rd_aclk) begin
    if (rd_rst_sync3_reg) begin
        wr_ptr_gray_sync1_reg <= {ADDR_WIDTH+1{1'b0}};
        wr_ptr_gray_sync2_reg <= {ADDR_WIDTH+1{1'b0}};
    end else begin
        wr_ptr_gray_sync1_reg <= wr_ptr_gray_reg;
        wr_ptr_gray_sync2_reg <= wr_ptr_gray_sync1_reg;
    end
end

// Read logic
always @* begin
    read = 1'b0;

    rd_ptr_next = rd_ptr_reg;
    rd_ptr_gray_next = rd_ptr_gray_reg;

    mem_read_data_valid_next = mem_read_data_valid_reg;

    //TODO: complete the output read logic;
    // ts is done

    if (~mem_read_data_valid_reg || ~rd_axis_vld_reg || rd_axis_rdy) begin
        if (~empty) begin
            read = 1'b1;
            mem_read_data_valid_next = 1'b1;
            rd_ptr_next = rd_ptr_reg + 1;
            rd_ptr_gray_next = rd_ptr_next ^ (rd_ptr_next >> 1);
        end else begin
            mem_read_data_valid_next = 1'b0;
        end
    end
end

always @(posedge rd_aclk) begin
    if (rd_rst_sync3_reg) begin
        rd_ptr_reg <= {ADDR_WIDTH+1{1'b0}};
        rd_ptr_gray_reg <= {ADDR_WIDTH+1{1'b0}};
        mem_read_data_valid_reg <= 1'b0;
    end else begin
        rd_ptr_reg <= rd_ptr_next;
        rd_ptr_gray_reg <= rd_ptr_gray_next;
        mem_read_data_valid_reg <= mem_read_data_valid_next;
    end

    rd_addr_reg <= rd_ptr_next;

    if (read) begin
        mem_read_data_reg <= mem[rd_addr_reg[ADDR_WIDTH-1:0]];
    end
end

// Output register
always @* begin
    store_output = 1'b0;

    rd_axis_vld_next = rd_axis_vld_reg;

    //TODO: complete the output register logic;

    if (~rd_axis_vld_reg || rd_axis_rdy) begin
        store_output = 1'b1;
        rd_axis_vld_next = mem_read_data_valid_reg;
    end

end

always @(posedge rd_aclk) begin
    if (rd_rst_sync3_reg) begin
        rd_axis_vld_reg <= 1'b0;
    end else begin
        rd_axis_vld_reg <= rd_axis_vld_next;
    end

    if (store_output) begin
        rd_data_reg <= mem_read_data_reg;
    end
end

endmodule

lab4/tb_simple.v
`timescale 1ns / 1ps
module tb_simple (
    input  wire        clk,
    input  wire        reset,
    input  wire [31:0] wr_data,
    input  wire        wr_vld,
    output wire        wr_rdy,
    output wire [31:0] rd_data,
    output wire        rd_vld,
    input  wire        rd_rdy
);

axis_fifo #(
    .ADDR_WIDTH(4),
    .AXIS_DATA_WIDTH(32)
) dut (
    .wr_aclk(clk), .wr_rstn(!reset),
    .wr_axis_data(wr_data), .wr_axis_vld(wr_vld), .wr_axis_rdy(wr_rdy),
    .rd_aclk(clk), .rd_rstn(!reset),
    .rd_axis_data(rd_data), .rd_axis_vld(rd_vld), .rd_axis_rdy(rd_rdy)
);

endmodule

lab4/trace_simple.vcd
$version Generated by VerilatedVcd $end
$timescale 1ps $end
 $scope module TOP $end
  $var wire 1 c clk $end
  $var wire 1 d reset $end
  $var wire 32 e wr_data [31:0] $end
  $var wire 1 f wr_vld $end
  $var wire 1 g wr_rdy $end
  $var wire 32 h rd_data [31:0] $end
  $var wire 1 i rd_vld $end
  $var wire 1 j rd_rdy $end
  $scope module tb_simple $end
   $var wire 1 c clk $end
   $var wire 1 d reset $end
   $var wire 32 e wr_data [31:0] $end
   $var wire 1 f wr_vld $end
   $var wire 1 g wr_rdy $end
   $var wire 32 h rd_data [31:0] $end
   $var wire 1 i rd_vld $end
   $var wire 1 j rd_rdy $end
   $scope module dut $end
    $var wire 32 o ADDR_WIDTH [31:0] $end
    $var wire 32 p AXIS_DATA_WIDTH [31:0] $end
    $var wire 1 c wr_aclk $end
    $var wire 1 k wr_rstn $end
    $var wire 32 e wr_axis_data [31:0] $end
    $var wire 1 f wr_axis_vld $end
    $var wire 1 g wr_axis_rdy $end
    $var wire 1 c rd_aclk $end
    $var wire 1 k rd_rstn $end
    $var wire 32 h rd_axis_data [31:0] $end
    $var wire 1 i rd_axis_vld $end
    $var wire 1 j rd_axis_rdy $end
    $var wire 5 + wr_ptr_reg [4:0] $end
    $var wire 5 # wr_ptr_next [4:0] $end
    $var wire 5 , wr_ptr_gray_reg [4:0] $end
    $var wire 5 $ wr_ptr_gray_next [4:0] $end
    $var wire 5 - wr_addr_reg [4:0] $end
    $var wire 5 . rd_ptr_reg [4:0] $end
    $var wire 5 % rd_ptr_next [4:0] $end
    $var wire 5 / rd_ptr_gray_reg [4:0] $end
    $var wire 5 & rd_ptr_gray_next [4:0] $end
    $var wire 5 0 rd_addr_reg [4:0] $end
    $var wire 5 1 wr_ptr_gray_sync1_reg [4:0] $end
    $var wire 5 2 wr_ptr_gray_sync2_reg [4:0] $end
    $var wire 5 3 rd_ptr_gray_sync1_reg [4:0] $end
    $var wire 5 4 rd_ptr_gray_sync2_reg [4:0] $end
    $var wire 1 5 wr_rst_sync1_reg $end
    $var wire 1 6 wr_rst_sync2_reg $end
    $var wire 1 7 wr_rst_sync3_reg $end
    $var wire 1 8 rd_rst_sync1_reg $end
    $var wire 1 9 rd_rst_sync2_reg $end
    $var wire 1 : rd_rst_sync3_reg $end
    $var wire 33 ; mem[0] [32:0] $end
    $var wire 33 = mem[1] [32:0] $end
    $var wire 33 ? mem[2] [32:0] $end
    $var wire 33 A mem[3] [32:0] $end
    $var wire 33 C mem[4] [32:0] $end
    $var wire 33 E mem[5] [32:0] $end
    $var wire 33 G mem[6] [32:0] $end
    $var wire 33 I mem[7] [32:0] $end
    $var wire 33 K mem[8] [32:0] $end
    $var wire 33 M mem[9] [32:0] $end
    $var wire 33 O mem[10] [32:0] $end
    $var wire 33 Q mem[11] [32:0] $end
    $var wire 33 S mem[12] [32:0] $end
    $var wire 33 U mem[13] [32:0] $end
    $var wire 33 W mem[14] [32:0] $end
    $var wire 33 Y mem[15] [32:0] $end
    $var wire 33 [ mem_read_data_reg [32:0] $end
    $var wire 1 ] mem_read_data_valid_reg $end
    $var wire 1 ' mem_read_data_valid_next $end
    $var wire 33 l mem_write_data [32:0] $end
    $var wire 33 ^ rd_data_reg [32:0] $end
    $var wire 1 ` rd_axis_vld_reg $end
    $var wire 1 ( rd_axis_vld_next $end
    $var wire 1 a full $end
    $var wire 1 b empty $end
    $var wire 1 n write $end
    $var wire 1 ) read $end
    $var wire 1 * store_output $end
   $upscope $end
  $upscope $end
 $upscope $end
$enddefinitions $end


#0
b00000 #
b00000 $
b00000 %
b00000 &
0'
0(
0)
1*
b00000 +
b00000 ,
b00000 -
b00000 .
b00000 /
b00000 0
b00000 1
b00000 2
b00000 3
b00000 4
15
16
17
18
19
1:
b000000000000000000000000000000000 ;
b000000000000000000000000000000000 =
b000000000000000000000000000000000 ?
b000000000000000000000000000000000 A
b000000000000000000000000000000000 C
b000000000000000000000000000000000 E
b000000000000000000000000000000000 G
b000000000000000000000000000000000 I
b000000000000000000000000000000000 K
b000000000000000000000000000000000 M
b000000000000000000000000000000000 O
b000000000000000000000000000000000 Q
b000000000000000000000000000000000 S
b000000000000000000000000000000000 U
b000000000000000000000000000000000 W
b000000000000000000000000000000000 Y
b000000000000000000000000000000000 [
0]
b000000000000000000000000000000000 ^
0`
0a
1b
0c
1d
b00000000000000000000000000000000 e
0f
0g
b00000000000000000000000000000000 h
0i
0j
0k
b000000000000000000000000000000000 l
0n
b00000000000000000000000000000100 o
b00000000000000000000000000100000 p
#1
1c
#2
0c
#3
1c
#4
0c
#5
1c
#6
0c
#7
1c
#8
0c
#9
1c
#10
0c
0d
1k
#11
05
08
1c
#12
0c
#13
06
09
1c
#14
b00000000000000000000000000001010 e
1f
b000000000000000000000000000001010 l
#15
0c
#16
b00001 #
b00001 $
07
0:
1c
b00000000000000000000000000010100 e
1g
b000000000000000000000000000010100 l
1n
#17
0c
#18
b00010 #
b00011 $
b00001 +
b00001 ,
b00001 -
b000000000000000000000000000011110 ;
1c
b00000000000000000000000000011110 e
b000000000000000000000000000011110 l
#19
0c
#20
b00011 #
b00010 $
b00010 +
b00011 ,
b00010 -
b00001 1
b000000000000000000000000000101000 =
1c
b00000000000000000000000000101000 e
b000000000000000000000000000101000 l
#21
0c
#22
b00100 #
b00110 $
b00001 %
b00001 &
1'
1)
b00011 +
b00010 ,
b00011 -
b00011 1
b00001 2
b000000000000000000000000000110010 ?
0b
1c
b00000000000000000000000000110010 e
b000000000000000000000000000110010 l
#23
0c
#24
b00011 #
b00010 $
0f
0n
#25
b00010 %
b00011 &
1(
b00001 .
b00001 /
b00001 0
b00010 1
b00011 2
b000000000000000000000000000011110 [
1]
1c
#26
0c
#27
0)
0*
b00010 .
b00011 /
b00010 0
b00010 2
b00001 3
b000000000000000000000000000101000 [
b000000000000000000000000000011110 ^
1`
1c
b00000000000000000000000000011110 h
1i
#28
0c
#29
b00011 3
b00001 4
1c
#30
0c
#31
b00011 4
1c
#32
0c
#33
1c
#34
b00011 %
b00010 &
1)
1*
1j
#35
0c
#36
0'
0)
b00011 .
b00010 /
b00011 0
b000000000000000000000000000110010 [
b000000000000000000000000000101000 ^
1b
1c
b00000000000000000000000000101000 h
#37
0c
#38
0(
b00010 3
0]
b000000000000000000000000000110010 ^
1c
b00000000000000000000000000110010 h
#39
0c
#40
b00010 4
0`
1c
0i
